gpke_calendar/__init__.py
gpke_calendar/gpke_calendar.py
gpke_calendar/data/2006.json
gpke_calendar/data/2007.json
gpke_calendar/data/2008.json
gpke_calendar/data/2009.json
gpke_calendar/data/2010.json
gpke_calendar/data/2011.json
gpke_calendar/data/2012.json
gpke_calendar/data/2013.json
gpke_calendar/data/2014.json
gpke_calendar/data/2015.json
gpke_calendar/data/2016.json
gpke_calendar/data/2017.json
gpke_calendar/data/2018.json
gpke_calendar/data/2019.json
gpke_calendar/data/2020.json
gpke_calendar/data/2021.json
gpke_calendar/data/2022.json
gpke_calendar/data/2023.json
gpke_calendar/data/2024.json
gpke_calendar/data/2025.json
gpke_calendar/data/2026.json
gpke_calendar/data/2027.json
gpke_calendar/data/2028.json
gpke_calendar-0.3.dist-info/DESCRIPTION.rst
gpke_calendar-0.3.dist-info/METADATA
gpke_calendar-0.3.dist-info/RECORD
gpke_calendar-0.3.dist-info/WHEEL
gpke_calendar-0.3.dist-info/metadata.json
gpke_calendar-0.3.dist-info/top_level.txt
