Metadata-Version: 2.0
Name: gpke-calendar
Version: 0.3
Summary: gpke calendar
Home-page: https://bitbucket.org/kingmray/django-google-calendar
Author: Raymond Schmidt
Author-email: UNKNOWN
License: BSD License
Platform: UNKNOWN
Requires-Dist: workdays
